{
    "os": "macOS-12.1-arm64-arm-64bit",
    "python": "3.8.9",
    "heartbeatAt": "2023-01-05T10:52:59.300016",
    "startedAt": "2023-01-05T10:52:58.719042",
    "docker": null,
    "cuda": null,
    "args": [],
    "state": "running",
    "program": "src/models/train_model.py",
    "codePath": "MLops-2023/src/models/train_model.py",
    "git": {
        "remote": "https://github.com/abzink/MLops-2023.git",
        "commit": "6b3ce1869d391cf1d24e7044cd1a747f76185361"
    },
    "email": "s213027@student.dtu.dk",
    "root": "/Users/annabzinkowska/DTU/MLops/MLops-2023",
    "host": "Annas-MacBook-Pro-2.local",
    "username": "annabzinkowska",
    "executable": "/Applications/Xcode.app/Contents/Developer/usr/bin/python3",
    "cpu_count": 8,
    "cpu_count_logical": 8,
    "disk": {
        "total": 228.27386474609375,
        "used": 14.672481536865234
    },
    "gpuapple": {
        "type": "arm",
        "vendor": "Apple"
    },
    "memory": {
        "total": 8.0
    }
}
